{"sourceFile": [{
      "name": "",
      "directive": [
        {
          "functionName": "generate_rand",
          "label": "",
          "functionLabel": "",
          "pragma": {"name": "INLINE"}
        },
        {
          "functionName": "monte_carlo_both_price",
          "label": "GAUSS_GEN_LABEL",
          "functionLabel": "",
          "pragma": {"name": "PIPELINE"}
        },
        {
          "functionName": "monte_carlo_both_price",
          "label": "SIMS_LABEL",
          "functionLabel": "",
          "pragma": {
            "name": "PIPELINE",
            "option": [{
                "name": "II",
                "value": "1"
              }]
          }
        }
      ]
    }]}
